<?xml version="1.0" encoding="utf-8"?>
<localization>
	<entity id="document-name">
		<locale lang="fr">filtre de paiement</locale>
	</entity>
	<entity id="label">
		<locale lang="fr">libellé</locale>
		<locale lang="en">label</locale>
	</entity>
	<entity id="label-help">
		<locale lang="fr">libellé utilisé en backoffice pour identifier le filtre.</locale>
		<locale lang="en">label used in backoffice only.</locale>
	</entity>
	<entity id="shop">
		<locale lang="fr">boutique</locale>
		<locale lang="en">shop</locale>
	</entity>
	<entity id="connector">
		<locale lang="fr">Mode de paiement</locale>
	</entity>
	<entity id="connector-help">
		<locale lang="fr">mode de paiement associé au filtre. Lorsque le filtre est applicable, ce mode de paiement sera autorisé pour la commande en cours.</locale>
	</entity>
	<entity id="query">
		<locale lang="fr">Conditions d'application</locale>
	</entity>
	<entity id="query-help">
		<locale lang="fr">Conditions d'application du filtre de paiement, évalué à la troisième étape du processus de commande standard.</locale>
	</entity>
</localization>