<?xml version="1.0" encoding="utf-8"?>
<localization>
	<entity id="createshop">
		<locale lang="fr">créer une boutique</locale>
		<locale lang="en">create shop</locale>
	</entity>
	<entity id="createtopshelf">
		<locale lang="fr">créer un rayon de premier niveau</locale>
		<locale lang="en">create top shelf</locale>
	</entity>
	<entity id="createshelf">
		<locale lang="fr">créer un rayon</locale>
		<locale lang="en">create shelf</locale>
		<locale lang="de">Neues Regal</locale>
	</entity>
	<entity id="createdeclinedproduct">
		<locale lang="fr">créer un produit décliné</locale>
		<locale lang="en">create product declined</locale>
	</entity>
	<entity id="createsimpleproduct">
		<locale lang="fr">créer un produit simple</locale>
		<locale lang="en">create simple product</locale>
	</entity>
	<entity id="createbundleproduct">
		<locale lang="fr">créer un groupe de produit</locale>
		<locale lang="en">create bundle product</locale>
	</entity>
	<entity id="createkit">
		<locale lang="fr">créer un kit</locale>
		<locale lang="en">create kit</locale>
	</entity>
	<entity id="createVirtualproduct">
		<locale lang="fr">créer un produit à télécharger</locale>
		<locale lang="en">create virtual product</locale>
	</entity>
	
	<entity id="Create-Price">
		<locale lang="fr">créer un prix normal</locale>
		<locale lang="en">create normal price</locale>
		<locale lang="de">Neuer normaler Preis</locale>
	</entity>
	<entity id="createRootfolder_">
		<locale lang="fr">créer...</locale>
		<locale lang="en">create...</locale>
	</entity>
	<entity id="createShelf_">
		<locale lang="fr">créer...</locale>
		<locale lang="en">create...</locale>
	</entity>
	<entity id="createTopshelf_">
		<locale lang="fr">créer...</locale>
		<locale lang="en">create...</locale>
	</entity>
	<entity id="createShopfolder_">
		<locale lang="fr">créer...</locale>
		<locale lang="en">create...</locale>
	</entity>
	<entity id="createDeclinedproduct_">
		<locale lang="fr">créer...</locale>
		<locale lang="en">create...</locale>
	</entity>
	<entity id="createFilter_">
		<locale lang="fr">créer...</locale>
		<locale lang="en">create...</locale>
	</entity>
	<entity id="createshippingfilter">
		<locale lang="fr">créer un filtre de livraison</locale>
	</entity>
	<entity id="createpaymentfilter">
		<locale lang="fr">créer un filtre de paiement</locale>
	</entity>
	<entity id="compileProduct">
		<locale lang="fr">Actualiser</locale>
	</entity>
	<entity id="exportalertinfos">
		<locale lang="fr">exporter les alertes</locale>
	</entity>
	<entity id="edit-price">
		<locale lang="fr">editer le prix</locale>
	</entity>
	<entity id="initdefaultstructure">
		<locale lang="fr">créer les pages par défaut</locale>
	</entity>
	<entity id="shop-already-contains-pages">
		<locale lang="fr">cette boutique contient déjà des pages.</locale>
	</entity>
	<entity id="invalid-shop">
		<locale lang="fr">boutique non valide.</locale>
	</entity>
	<entity id="invalid-shop-import-script">
		<locale lang="fr">le script d'initialisation est illisible.</locale>
	</entity>
	<entity id="showPublicationInShops">
		<locale lang="fr">publication dans les boutiques</locale>
	</entity>
	<entity id="openTreeNodeOrder">
		<locale lang="fr">définir l'ordre des rayons</locale>
	</entity>
	<entity id="openOrderProductsInShelf">
		<locale lang="fr">définir l'ordre des produits</locale>
	</entity>
</localization>